{"cameraMode":{"drawMode":0,"name":"Shaded","section":"Shading Mode"},"sceneLighting":true,"audioPlay":false,"sceneViewState":{"showFog":true,"showMaterialUpdate":false,"showSkybox":true,"showFlares":true,"showImageEffects":true,"showParticleSystems":true,"showVisualEffectGraphs":true,"m_FxEnabled":true},"in2DMode":false,"pivot":{"x":9.381598472595215,"y":6.592434406280518,"z":-3.3202133178710939},"rotation":{"x":-0.022558605298399926,"y":-0.977055013179779,"z":0.1345146745443344,"w":-0.16390791535377503},"size":0.47712093591690066,"orthographic":false}